{
  "currencies": [
    {
      "name": "QIWI RUB",
      "id": "QIWIRUR"
    },
    {
      "name": "QIWI KZT",
      "id": "QWKZT"
    },
    {
      "name": "ЮMoney (Я.Деньги)",
      "id": "YAMRUB"
    },
    {
      "name": "WMZ",
      "id": "WMZ"
    },
    {
      "name": "WMR",
      "id": "WMR"
    },
    {
      "name": "WME",
      "id": "WME"
    },
    {
      "name": "WMU",
      "id": "WMU"
    },
    {
      "name": "WMB",
      "id": "WMB"
    },
    {
      "name": "WMY",
      "id": "WMY"
    },
    {
      "name": "WMK",
      "id": "WMK"
    },
    {
      "name": "WMG",
      "id": "WMG"
    },
    {
      "name": "WMX",
      "id": "WMX"
    },
    {
      "name": "Paymer RUB",
      "id": "PMRRUB"
    },
    {
      "name": "Paymer USD",
      "id": "PMRUSD"
    },
    {
      "name": "Paymer UAH",
      "id": "PMRUAH"
    },
    {
      "name": "Perfect Money USD",
      "id": "PMUSD"
    },
    {
      "name": "Perfect Money EUR",
      "id": "PMEUR"
    },
    {
      "name": "Perfect Money BTC",
      "id": "PMBTC"
    },
    {
      "name": "PM e-Voucher USD",
      "id": "PMVUSD"
    },
    {
      "name": "AdvCash USD",
      "id": "ADVCUSD"
    },
    {
      "name": "AdvCash RUB",
      "id": "ADVCRUB"
    },
    {
      "name": "AdvCash UAH",
      "id": "ADVCUAH"
    },
    {
      "name": "AdvCash EUR",
      "id": "ADVCEUR"
    },
    {
      "name": "AdvCash KZT",
      "id": "ADVCKZT"
    },
    {
      "name": "Payeer USD",
      "id": "PRUSD"
    },
    {
      "name": "Payeer RUB",
      "id": "PRRUB"
    },
    {
      "name": "Payeer EUR",
      "id": "PREUR"
    },
    {
      "name": "Capitalist USD",
      "id": "CPTSUSD"
    },
    {
      "name": "Capitalist RUB",
      "id": "CPTSRUB"
    },
    {
      "name": "PayPal USD",
      "id": "PPUSD"
    },
    {
      "name": "PayPal EUR",
      "id": "PPEUR"
    },
    {
      "name": "PayPal RUB",
      "id": "PPRUB"
    },
    {
      "name": "PayPal GBP",
      "id": "PPGBP"
    },
    {
      "name": "PayPal CAD",
      "id": "PPCAD"
    },
    {
      "name": "PayPal AUD",
      "id": "PPAUD"
    },
    {
      "name": "Skrill USD",
      "id": "Skrill"
    },
    {
      "name": "Skrill EUR",
      "id": "SKLEUR"
    },
    {
      "name": "W1 USD",
      "id": "WOUSD"
    },
    {
      "name": "W1 RUB",
      "id": "WORUB"
    },
    {
      "name": "W1 UAH",
      "id": "WOUAH"
    },
    {
      "name": "Paxum USD",
      "id": "PXMUSD"
    },
    {
      "name": "Paxum EUR",
      "id": "PXMEUR"
    },
    {
      "name": "EKZT",
      "id": "EKZT"
    },
    {
      "name": "Epay USD",
      "id": "EPAYUSD"
    },
    {
      "name": "Epay EUR",
      "id": "EPAYEUR"
    },
    {
      "name": "Epayments USD",
      "id": "EPMUSD"
    },
    {
      "name": "Epayments EUR",
      "id": "EPMEUR"
    },
    {
      "name": "STrustPay USD",
      "id": "STPUSD"
    },
    {
      "name": "Alipay CNY",
      "id": "ALPCNY"
    },
    {
      "name": "Global Money UAH",
      "id": "GMUAH"
    },
    {
      "name": "Idram AMD",
      "id": "EDram"
    },
    {
      "name": "InstaForex USD",
      "id": "INFXUSD"
    },
    {
      "name": "NixMoney USD",
      "id": "NixMoney"
    },
    {
      "name": "NixMoney EUR",
      "id": "NIXEUR"
    },
    {
      "name": "NixMoney BTC",
      "id": "NIXBTC"
    },
    {
      "name": "Neteller USD",
      "id": "NTLRUSD"
    },
    {
      "name": "Neteller EUR",
      "id": "NTLREUR"
    },
    {
      "name": "PaySera USD",
      "id": "PSRUSD"
    },
    {
      "name": "PaySera EUR",
      "id": "PSREUR"
    },
    {
      "name": "FasaPay USD",
      "id": "FPUSD"
    },
    {
      "name": "FasaPay IDR",
      "id": "FPIDR"
    },
    {
      "name": "EcoPayz RUB",
      "id": "ECOPAYZRUB"
    },
    {
      "name": "EcoPayz USD",
      "id": "ECOPAYZUSD"
    },
    {
      "name": "EcoPayz EUR",
      "id": "ECOPAYZEUR"
    },
    {
      "name": "WeChat CNY",
      "id": "WCTCNY"
    },
    {
      "name": "Наличные USD",
      "id": "CashUSD"
    },
    {
      "name": "Наличные RUB",
      "id": "CashRUB"
    },
    {
      "name": "Наличные EUR",
      "id": "CashEUR"
    },
    {
      "name": "Наличные UAH",
      "id": "CashUAH"
    },
    {
      "name": "Наличные KZT",
      "id": "CASHKZT"
    },
    {
      "name": "Альфа-Банк CASH-IN RUB",
      "id": "ACCRUB"
    },
    {
      "name": "Альфа-Банк CASH-IN USD",
      "id": "ACCUSD"
    },
    {
      "name": "Альфа-Банк CASH-IN EUR",
      "id": "ACCEUR"
    },
    {
      "name": "Tinkoff cash-in RUB",
      "id": "TCSBCRUB"
    },
    {
      "name": "Сбербанк RUB",
      "id": "SBRFRUB"
    },
    {
      "name": "Сбербанк KZT",
      "id": "SBERKZT"
    },
    {
      "name": "Сбербанк UAH",
      "id": "SBERUAH"
    },
    {
      "name": "Альфа Банк RUB",
      "id": "ACRUB"
    },
    {
      "name": "Альфа Банк UAH",
      "id": "ACUAH"
    },
    {
      "name": "Тинькофф",
      "id": "TKS"
    },
    {
      "name": "Приват24 UAH",
      "id": "P24UAH"
    },
    {
      "name": "Приват24 USD",
      "id": "P24USD"
    },
    {
      "name": "Monobank UAH",
      "id": "MONOBUAH"
    },
    {
      "name": "Ощадбанк",
      "id": "OSHBUAH"
    },
    {
      "name": "Телебанк ВТБ24",
      "id": "TBRUB"
    },
    {
      "name": "Газпромбанк",
      "id": "GPBRUB"
    },
    {
      "name": "Беларусбанк BYN",
      "id": "BLRBBYN"
    },
    {
      "name": "Райффайзен RUB",
      "id": "RFBRUB"
    },
    {
      "name": "Райффайзен UAH",
      "id": "RFBUAH"
    },
    {
      "name": "Kaspi Bank KZT",
      "id": "KSPBKZT"
    },
    {
      "name": "Jysan Bank KZT",
      "id": "JSNBKZT"
    },
    {
      "name": "Русский Стандарт",
      "id": "RUSSTRUB"
    },
    {
      "name": "Авангард",
      "id": "AVBRUB"
    },
    {
      "name": "Почта Банк",
      "id": "POSTBRUB"
    },
    {
      "name": "Промсвязьбанк",
      "id": "PSBRUB"
    },
    {
      "name": "Открытие",
      "id": "OPENBANK"
    },
    {
      "name": "Кукуруза",
      "id": "KUKRUB"
    },
    {
      "name": "Казкоммерцбанк",
      "id": "KKBKZT"
    },
    {
      "name": "HalykBank",
      "id": "HALYKBANK"
    },
    {
      "name": "ForteBank KZT",
      "id": "FRTBKZT"
    },
    {
      "name": "ПУМБ UAH",
      "id": "PUMBUAH"
    },
    {
      "name": "ОТП Банк RUB",
      "id": "OTPBRUB"
    },
    {
      "name": "ОТП Банк UAH",
      "id": "OTPBUAH"
    },
    {
      "name": "Universal Bank",
      "id": "UNVBUAH"
    },
    {
      "name": "Homecredit",
      "id": "HCBRUB"
    },
    {
      "name": "UniCredit RUB",
      "id": "UNCBRUB"
    },
    {
      "name": "UniCredit UAH",
      "id": "UNCBUAH"
    },
    {
      "name": "UkrSibBank UAH",
      "id": "USBUAH"
    },
    {
      "name": "АТФ Банк KZT",
      "id": "ATFBKZT"
    },
    {
      "name": "Евразийский Банк KZT",
      "id": "EURBKZT"
    },
    {
      "name": "МИР",
      "id": "MIRCRUB"
    },
    {
      "name": "Trust",
      "id": "TRBRUB"
    },
    {
      "name": "РНКБ",
      "id": "RNKBRUB"
    },
    {
      "name": "МТС Банк",
      "id": "MTSBRUB"
    },
    {
      "name": "Ак Барс Банк RUB",
      "id": "AKBBRUB"
    },
    {
      "name": "Связной банк",
      "id": "SVBRUB"
    },
    {
      "name": "Россельхозбанк",
      "id": "RSHBRUB"
    },
    {
      "name": "Карты UZCARD",
      "id": "UZCUZS"
    },
    {
      "name": "Visa/Master UAH",
      "id": "CardUAH"
    },
    {
      "name": "Visa/Master RUB",
      "id": "CardRUB"
    },
    {
      "name": "Visa/Master USD",
      "id": "CardUSD"
    },
    {
      "name": "Visa/Master EUR",
      "id": "CardEUR"
    },
    {
      "name": "Visa/Master KZT",
      "id": "CARDKZT"
    },
    {
      "name": "Visa/Master BYN",
      "id": "CARDBYN"
    },
    {
      "name": "Visa/Master AMD",
      "id": "CARDAMD"
    },
    {
      "name": "Visa/Master THB",
      "id": "CARDTHB"
    },
    {
      "name": "Visa/Master MDL",
      "id": "CARDMDL"
    },
    {
      "name": "Unionpay",
      "id": "UNPCNY"
    },
    {
      "name": "Счет в банке для ИП или Юр. лиц",
      "id": "STLMRUB"
    },
    {
      "name": "Перевод UAH",
      "id": "WIREUAH"
    },
    {
      "name": "Перевод USD",
      "id": "WireUSD"
    },
    {
      "name": "Перевод RUB",
      "id": "WireRUB"
    },
    {
      "name": "Перевод EUR",
      "id": "WireEUR"
    },
    {
      "name": "Перевод KZT",
      "id": "WIREKZT"
    },
    {
      "name": "Перевод GBP",
      "id": "WIREGBP"
    },
    {
      "name": "Перевод CNY",
      "id": "WIRECNY"
    },
    {
      "name": "Перевод THB",
      "id": "WIRETHB"
    },
    {
      "name": "Перевод JPY",
      "id": "WIREJPY"
    },
    {
      "name": "Tinkoff Qr-коды RUB",
      "id": "TCSBQRUB"
    },
    {
      "name": "Перевод PLN",
      "id": "WIREPLN"
    },
    {
      "name": "Росбанк",
      "id": "ROSBRUB"
    },
    {
      "name": "Western USD",
      "id": "WUUSD"
    },
    {
      "name": "Western RUB",
      "id": "WURUB"
    },
    {
      "name": "Western EUR",
      "id": "WUEUR"
    },
    {
      "name": "Moneygram USD",
      "id": "MGUSD"
    },
    {
      "name": "Moneygram EUR",
      "id": "MGEUR"
    },
    {
      "name": "SEPA EUR",
      "id": "SEPAEUR"
    },
    {
      "name": "SEPA USD",
      "id": "SEPAUSD"
    },
    {
      "name": "Contact RUB",
      "id": "CNTRUB"
    },
    {
      "name": "Contact USD",
      "id": "CNTUSD"
    },
    {
      "name": "Contact EUR",
      "id": "CNTEUR"
    },
    {
      "name": "Корона USD",
      "id": "GCMTUSD"
    },
    {
      "name": "Корона RUB",
      "id": "GCMTRUB"
    },
    {
      "name": "Sigue USD",
      "id": "SGMTUSD"
    },
    {
      "name": "Sigue EUR",
      "id": "SGMTEUR"
    },
    {
      "name": "Ria Financial USD",
      "id": "RMTFUSD"
    },
    {
      "name": "Ria Financial EUR",
      "id": "RMTFEUR"
    },
    {
      "name": "Unistream USD",
      "id": "USTMUSD"
    },
    {
      "name": "Unistream RUB",
      "id": "USTMRUB"
    },
    {
      "name": "Мобильная связь РФ",
      "id": "MWRUB"
    },
    {
      "name": "Bitcoin (BTC)",
      "id": "BTC"
    },
    {
      "name": "Bitcoin BEP20 (BTC)",
      "id": "BTCBEP20"
    },
    {
      "name": "Wrapped Bitcoin (WBTC)",
      "id": "WBTC"
    },
    {
      "name": "Ethereum (ETH)",
      "id": "ETH"
    },
    {
      "name": "Ethereum BEP20 (ETH)",
      "id": "ETHBEP20"
    },
    {
      "name": "Ethereum Classic (ETC)",
      "id": "ETC"
    },
    {
      "name": "Ripple (XRP)",
      "id": "XRP"
    },
    {
      "name": "Tether ERC20 (USDT)",
      "id": "USDTERC"
    },
    {
      "name": "Tether TRC20 (USDT)",
      "id": "USDTTRC"
    },
    {
      "name": "Tether BEP20 (USDT)",
      "id": "USDTBEP20"
    },
    {
      "name": "Tether Omni (USDT)",
      "id": "USDT"
    },
    {
      "name": "Bitcoin Cash (BCH)",
      "id": "BCH"
    },
    {
      "name": "Bitcoin SV (BSV)",
      "id": "BSV"
    },
    {
      "name": "Litecoin (LTC)",
      "id": "LTC"
    },
    {
      "name": "Binance Coin (BNB)",
      "id": "BNB"
    },
    {
      "name": "Binance Coin BEP20 (BNB)",
      "id": "BNBBEP20"
    },
    {
      "name": "USD Coin (USDC)",
      "id": "USDC"
    },
    {
      "name": "Cardano (ADA)",
      "id": "ADA"
    },
    {
      "name": "Tron (TRX)",
      "id": "TRX"
    },
    {
      "name": "Monero (XMR)",
      "id": "XMR"
    },
    {
      "name": "Stellar (XLM)",
      "id": "XLM"
    },
    {
      "name": "EOS (EOS)",
      "id": "EOS"
    },
    {
      "name": "DASH (DASH)",
      "id": "DASH"
    },
    {
      "name": "Dogecoin (DOGE)",
      "id": "DGC"
    },
    {
      "name": "Lisk (LSK)",
      "id": "LSK"
    },
    {
      "name": "Namecoin (NMC)",
      "id": "NMC"
    },
    {
      "name": "Qtum (QTUM)",
      "id": "QTUM"
    },
    {
      "name": "TrueUSD (TUSD)",
      "id": "TUSD"
    },
    {
      "name": "Verge (XVG)",
      "id": "XVG"
    },
    {
      "name": "WAVES (WAVES)",
      "id": "WAVES"
    },
    {
      "name": "Zcash (ZEC)",
      "id": "ZEC"
    },
    {
      "name": "NXT",
      "id": "NXT"
    },
    {
      "name": "Decred (DCR)",
      "id": "DCR"
    },
    {
      "name": "Gnosis (GNO)",
      "id": "GNO"
    },
    {
      "name": "IOTA (MIOTA)",
      "id": "IOTA"
    },
    {
      "name": "NEM (XEM)",
      "id": "XEM"
    },
    {
      "name": "Bitcoin Gold (BTG)",
      "id": "BTG"
    },
    {
      "name": "NEO (NEO)",
      "id": "NEO"
    },
    {
      "name": "OmiseGO (OMG)",
      "id": "OMG"
    },
    {
      "name": "Augur (REP)",
      "id": "REP"
    },
    {
      "name": "Peercoin (PPC)",
      "id": "PPC"
    },
    {
      "name": "VeChain (VET)",
      "id": "VET"
    },
    {
      "name": "Bytecoin (BCN)",
      "id": "BCN"
    },
    {
      "name": "Livecoin RUB",
      "id": "LVCNRUB"
    },
    {
      "name": "Livecoin USD",
      "id": "LVCNUSD"
    },
    {
      "name": "Pax Dollar (USDP)",
      "id": "USDP"
    },
    {
      "name": "DAI",
      "id": "DAI"
    },
    {
      "name": "0x (ZRX)",
      "id": "ZRX"
    },
    {
      "name": "Basic Attention Token (BAT)",
      "id": "BAT"
    },
    {
      "name": "Cosmos (ATOM)",
      "id": "ATOM"
    },
    {
      "name": "Chainlink (LINK)",
      "id": "LINK"
    },
    {
      "name": "Tezos (XTZ)",
      "id": "XTZ"
    },
    {
      "name": "BitTorrent (BTT)",
      "id": "BTT"
    },
    {
      "name": "Komodo (KMD)",
      "id": "KMD"
    },
    {
      "name": "ICON (ICX)",
      "id": "ICX"
    },
    {
      "name": "Ontology (ONT)",
      "id": "ONT"
    },
    {
      "name": "Polkadot (DOT)",
      "id": "DOT"
    },
    {
      "name": "Algorand (ALGO)",
      "id": "ALGO"
    },
    {
      "name": "Uniswap (UNI)",
      "id": "UNI"
    },
    {
      "name": "THETA",
      "id": "THETA"
    },
    {
      "name": "SushiSwap (SUSHI)",
      "id": "SUSHI"
    },
    {
      "name": "Binance USD (BUSD)",
      "id": "BUSD"
    },
    {
      "name": "Solana (SOL)",
      "id": "SOL"
    },
    {
      "name": "Ravecoin (RVN)",
      "id": "RVN"
    },
    {
      "name": "SHIBA INU (SHIB)",
      "id": "SHIB"
    },
    {
      "name": "Polygon (MATIC)",
      "id": "MATIC"
    },
    {
      "name": "Kusama (KSM)",
      "id": "KSM"
    },
    {
      "name": "Decentraland (MANA)",
      "id": "Mana"
    },
    {
      "name": "Avalanche (AVAX)",
      "id": "AVAX"
    },
    {
      "name": "Yearn.finance (YFI)",
      "id": "YFI"
    },
    {
      "name": "AAVE",
      "id": "AAVE"
    },
    {
      "name": "KAVA",
      "id": "KAVA"
    },
    {
      "name": "Terra (LUNA)",
      "id": "LUNA"
    }
  ]
}